wjx.py
give_me_a_chance-0.1.0.dist-info/METADATA
give_me_a_chance-0.1.0.dist-info/WHEEL
give_me_a_chance-0.1.0.dist-info/top_level.txt
give_me_a_chance-0.1.0.dist-info/RECORD
